boo/__init__.py
boo/cli.py
boo/columns.py
boo/dataframe/__init__.py
boo/dataframe/canonic.py
boo/dataframe/filter.py
boo/dataframe/util.py
boo/downloader.py
boo/okved/__init__.py
boo/okved/okved.py
boo/reader.py
boo/whatis.py
boo-0.2.0.dist-info/LICENSE
boo-0.2.0.dist-info/WHEEL
boo-0.2.0.dist-info/METADATA
boo-0.2.0.dist-info/RECORD
