Metadata-Version: 2.1
Name: boo
Version: 0.2.0
Summary: Russian corporate financial reports 2012-2018.
Author: Evgeniy Pogrebnyak
Author-email: e.pogrebnyak@gmail.com
Requires-Python: >=3.8,<4.0
Classifier: Programming Language :: Python :: 3
Classifier: Programming Language :: Python :: 3.8
Classifier: Programming Language :: Python :: 3.9
Requires-Dist: click (>=7.1.2,<8.0.0)
Requires-Dist: pandas (==1.1.5)
Requires-Dist: requests (>=2.25.1,<3.0.0)
Requires-Dist: tqdm (>=4.59.0,<5.0.0)
